xarray_video/__init__.py
xarray_video/backend.py
xarray_video/exceptions.py
xarray_video/videoarray.py
xarray_video/videodataset.py
xarray_video/codecs/__init__.py
xarray_video/codecs/h264.py
xarray_video-0.2.11.dist-info/AUTHORS.rst
xarray_video-0.2.11.dist-info/LICENSE
xarray_video-0.2.11.dist-info/METADATA
xarray_video-0.2.11.dist-info/WHEEL
xarray_video-0.2.11.dist-info/top_level.txt
xarray_video-0.2.11.dist-info/RECORD
