Metadata-Version: 2.1
Name: xarray-video
Version: 0.2.11
Summary: Xarray accessor and zarr codec for storing and accessing time and/or space stacked video
Home-page: https://github.com/oceanum/xarray-video
Author: Oceanum Developers
Author-email: developers@oceanum.science
License: MIT license
Keywords: oceanum,video,xarray
License-File: LICENSE
License-File: AUTHORS.rst
Requires-Dist: xarray
Requires-Dist: numcodecs
Requires-Dist: av
Requires-Dist: zarr
Provides-Extra: plotting
Requires-Dist: matplotlib ; extra == 'plotting'
